piket/__init__.py
piket/card.py
piket/constants.py
piket/converter.py
piket/pd.py
piket/py.typed
piket/base/level_base.py
piket/bin/linux-amd64/libnedclib.so
piket/bin/linux-amd64/nedcenc
piket/bin/linux-amd64/nevpk
piket/bin/macos-arm64/libnedclib.dylib
piket/bin/macos-arm64/nedcenc
piket/bin/macos-arm64/nevpk
piket/bin/windows-amd64/libnedclib.dll
piket/bin/windows-amd64/nedcenc.exe
piket/bin/windows-amd64/nevpk.exe
piket/connecting_pikmin/__init__.py
piket/connecting_pikmin/level.py
piket/connecting_pikmin/object.py
piket/connecting_pikmin/piki.py
piket/connecting_pikmin/tile.py
piket/marching_pikmin/__init__.py
piket/marching_pikmin/level.py
piket/marching_pikmin/piki.py
piket/marching_pikmin/tile.py
piket/plucking_pikmin/__init__.py
piket/plucking_pikmin/level.py
piket/plucking_pikmin/piki.py
piket/plucking_pikmin/player.py
piket/plucking_pikmin/tile.py
piket/treasure/__init__.py
piket/treasure/treasure.py
piket/treasure/treasure_sprite.py
piket/treasure/sprites/custom/fuel_reservoir.bin
piket/util/__init__.py
piket/util/decode.py
piket/util/encode.py
piket/util/get_id.py
piket/util/headerfix.py
piket-0.3.2.dist-info/licenses/LICENSE
piket-0.3.2.dist-info/METADATA
piket-0.3.2.dist-info/WHEEL
piket-0.3.2.dist-info/top_level.txt
piket-0.3.2.dist-info/RECORD
