Metadata-Version: 2.4
Name: piket
Version: 0.3.2
Summary: Pikmin e+ Card Tools, a library for manipulating Pikmin e+ cards
Author: plxl
Requires-Python: >=3.13
License-File: LICENSE
Requires-Dist: pillow==12.0.0
Provides-Extra: demo
Requires-Dist: tkinterdnd2==0.4.3; extra == "demo"
Dynamic: license-file
